zlxmcp/__init__.py
zlxmcp/api/__init__.py
zlxmcp/api/base.py
zlxmcp/api/company_base.py
zlxmcp/api/company_operation.py
zlxmcp/charts/__init__.py
zlxmcp/charts/charts.py
zlxmcp/mcp/__init__.py
zlxmcp/mcp/pd.py
zlxmcp/mcp/report.py
zlxmcp/mcp/server.py
zlxmcp/types/__init__.py
zlxmcp/types/schema.py
zlxmcp/types/types.py
zlxmcp/utils/__init__.py
zlxmcp/utils/encrypt.py
zlxmcp/utils/fetch.py
zlxmcp/utils/parse_sql.py
zlxmcp/utils/utils.py
zlxmcp-0.0.5.dist-info/METADATA
zlxmcp-0.0.5.dist-info/WHEEL
zlxmcp-0.0.5.dist-info/entry_points.txt
zlxmcp-0.0.5.dist-info/top_level.txt
zlxmcp-0.0.5.dist-info/RECORD
