Metadata-Version: 2.4
Name: zlxmcp
Version: 0.0.5
Summary: ZLX MCP Server
Requires-Python: >=3.10
Requires-Dist: click>=8.1.8
Requires-Dist: fastmcp>=2.2.8
Requires-Dist: gmssl>=3.2.2
Requires-Dist: pandas>=2.2.3
Requires-Dist: pydantic>=2.11.4
Requires-Dist: pyecharts>=2.0.8
Requires-Dist: requests>=2.32.3
Requires-Dist: tabulate>=0.9.0
Requires-Dist: weasyprint>=65.1
